deepwiki_cli/__init__.py
deepwiki_cli/query.py
deepwiki_cli/clients/__init__.py
deepwiki_cli/clients/dashscope_client.py
deepwiki_cli/clients/huggingface_embedder_client.py
deepwiki_cli/configs/__init__.py
deepwiki_cli/configs/compose_hydra.py
deepwiki_cli/configs/generator.yaml
deepwiki_cli/configs/main.yaml
deepwiki_cli/configs/rag.yaml
deepwiki_cli/configs/repo.yaml
deepwiki_cli/core/__init__.py
deepwiki_cli/core/types.py
deepwiki_cli/core/utils.py
deepwiki_cli/logger/__init__.py
deepwiki_cli/logger/logging_config.py
deepwiki_cli/rag/__init__.py
deepwiki_cli/rag/code_understanding.py
deepwiki_cli/rag/data_pipeline.py
deepwiki_cli/rag/dynamic_splitter_transformer.py
deepwiki_cli/rag/embedding.py
deepwiki_cli/rag/rag.py
deepwiki_cli/rag/retriever.py
deepwiki_cli/rag/splitter_factory.py
deepwiki_cli/rag/splitter/__init__.py
deepwiki_cli/rag/splitter/code_splitter.py
deepwiki_cli/rag/splitter/natural_language_splitter.py
deepwiki_cli-0.2.3.dist-info/licenses/LICENSE
deepwiki_cli-0.2.3.dist-info/METADATA
deepwiki_cli-0.2.3.dist-info/WHEEL
deepwiki_cli-0.2.3.dist-info/entry_points.txt
deepwiki_cli-0.2.3.dist-info/top_level.txt
deepwiki_cli-0.2.3.dist-info/RECORD
