Metadata-Version: 2.4
Name: deepwiki_cli
Version: 0.2.3
Summary: Repository Analysis and Query Library with RAG capabilities
Author-email: Haoyang Ma <haoyanghkust@gmail.com>
License: MIT License
Project-URL: Homepage, https://github.com/RAG4SE/deepwiki-cli
Project-URL: Documentation, https://github.com/RAG4SE/deepwiki-cli#readme
Project-URL: Repository, https://github.com/RAG4SE/deepwiki-cli
Project-URL: Bug Tracker, https://github.com/RAG4SE/deepwiki-cli/issues
Keywords: deepwiki,rag,llm
Classifier: Development Status :: 4 - Beta
Classifier: Intended Audience :: Developers
Classifier: Operating System :: OS Independent
Classifier: Programming Language :: Python :: 3
Classifier: Programming Language :: Python :: 3.9
Classifier: Programming Language :: Python :: 3.10
Classifier: Programming Language :: Python :: 3.11
Classifier: Programming Language :: Python :: 3.12
Classifier: Topic :: Software Development :: Libraries :: Python Modules
Classifier: Topic :: Scientific/Engineering :: Artificial Intelligence
Requires-Python: >=3.9
License-File: LICENSE
Requires-Dist: adalflow>=1.1.0
Requires-Dist: omegaconf>=2.3.0
Requires-Dist: hydra-core>=1.3.0
Requires-Dist: faiss-cpu>=1.7.0
Requires-Dist: tqdm>=4.64.0
Requires-Dist: openai>=1.0.0
Requires-Dist: tiktoken>=0.4.0
Requires-Dist: numpy>=1.21.0
Requires-Dist: pydantic>=2.0.0
Requires-Dist: PyYAML>=6.0
Requires-Dist: requests>=2.20.0
Requires-Dist: torch>=2.0.0
Requires-Dist: sentence-transformers>=2.2.0
Requires-Dist: rank-bm25>=0.2.2
Provides-Extra: dev
Requires-Dist: pytest; extra == "dev"
Requires-Dist: black; extra == "dev"
Requires-Dist: flake8; extra == "dev"
Requires-Dist: mypy; extra == "dev"
Requires-Dist: build; extra == "dev"
Requires-Dist: twine; extra == "dev"
Dynamic: license-file
